README.rst
setup.cfg
setup.py
camkes_cli/__init__.py
camkes_cli/__main__.py
camkes_cli/build.py
camkes_cli/clean.py
camkes_cli/cli.py
camkes_cli/common.py
camkes_cli/component.py
camkes_cli/defaults.py
camkes_cli/info.py
camkes_cli/init.py
camkes_cli/menuconfig.py
camkes_cli/new.py
camkes_cli/procedure.py
camkes_cli/run.py
camkes_cli/update.py
camkes_cli.egg-info/PKG-INFO
camkes_cli.egg-info/SOURCES.txt
camkes_cli.egg-info/dependency_links.txt
camkes_cli.egg-info/entry_points.txt
camkes_cli.egg-info/requires.txt
camkes_cli.egg-info/top_level.txt
camkes_cli/templates/app_templates/hello_world/app.camkes
camkes_cli/templates/app_templates/hello_world/src/components/HelloWorld/HelloWorld.camkes
camkes_cli/templates/app_templates/hello_world/src/components/HelloWorld/src/hello_world.c
camkes_cli/templates/base_templates/Kbuild
camkes_cli/templates/base_templates/Kconfig
camkes_cli/templates/base_templates/Makefile
camkes_cli/templates/base_templates/app.camkes
camkes_cli/templates/base_templates/config_aarch32
camkes_cli/templates/base_templates/config_x86
camkes_cli/templates/base_templates/config_x86_64
camkes_cli/templates/base_templates/gitignore
camkes_cli/templates/build_templates/sel4/Kconfig
camkes_cli/templates/part_templates/component.c
camkes_cli/templates/part_templates/component.camkes
camkes_cli/templates/part_templates/procedure.camkes