Metadata-Version: 1.0
Name: camkes-cli
Version: 0.4.0
Summary: Command line interface for the CAmkES component framework
Home-page: https://github.com/seL4proj/camkes-cli
Author: Stephen Sherratt
Author-email: Stephen.Sherratt@data61.csiro.au
License: BSD2
Keywords: camkes sel4
Platform: UNKNOWN
